fpptools/__init__.py
fpptools/fittinglist_str.txt
fpptools/fpptools.py
fpptools-0.1.1.dist-info/entry_points.txt
fpptools-0.1.1.dist-info/LICENSE
fpptools-0.1.1.dist-info/WHEEL
fpptools-0.1.1.dist-info/METADATA
fpptools-0.1.1.dist-info/RECORD
