Metadata-Version: 2.1
Name: fpptools
Version: 0.1.1
Summary: An FPPro debug CLI written in python3
Home-page: UNKNOWN
License: MIT
Author: andresperezcera
Author-email: andresperezcera@gmail.com
Requires-Python: >=3.6,<4.0
Classifier: Environment :: Console
Classifier: Environment :: Win32 (MS Windows)
Classifier: License :: OSI Approved :: MIT License
Classifier: Programming Language :: Python :: 3
Classifier: Programming Language :: Python :: 3.6
Classifier: Programming Language :: Python :: 3.7
Classifier: Topic :: Desktop Environment
Classifier: Topic :: Software Development :: Libraries :: Python Modules
Classifier: Topic :: Utilities
Requires-Dist: click (>=6.7,<7.0)
Requires-Dist: colorama (>=0.3.9,<0.4.0)
Requires-Dist: configparser (>=3.5,<4.0)
Requires-Dist: lxml (>=4.2,<5.0)
Requires-Dist: pymysql (>=0.9.2,<0.10.0)
Requires-Dist: pyodbc (>=4.0,<5.0)
